pypcc/model.py
pypcc-0.0.4.dist-info/LICENSE
pypcc-0.0.4.dist-info/METADATA
pypcc-0.0.4.dist-info/WHEEL
pypcc-0.0.4.dist-info/top_level.txt
pypcc-0.0.4.dist-info/RECORD
